{"cameraMode":{"drawMode":0,"name":"Shaded","section":"Shading Mode"},"sceneLighting":true,"audioPlay":false,"sceneViewState":{"showFog":true,"showMaterialUpdate":false,"showSkybox":true,"showFlares":true,"showImageEffects":true,"showParticleSystems":true},"in2DMode":false,"pivot":{"x":-2.0131349563598635,"y":-0.28530648350715639,"z":-8.16446590423584},"rotation":{"x":-0.1227722093462944,"y":0.5660819411277771,"z":-0.08573420345783234,"w":-0.8106345534324646},"size":10.22909927368164,"orthographic":false}